TDW8970/__init__.py
TDW8970/router.py
TDW8970-0.1.0.dist-info/LICENSE
TDW8970-0.1.0.dist-info/METADATA
TDW8970-0.1.0.dist-info/WHEEL
TDW8970-0.1.0.dist-info/top_level.txt
TDW8970-0.1.0.dist-info/RECORD
