Metadata-Version: 2.1
Name: TDW8970
Version: 0.1.0
Summary: A library for scraping ADSL connection statistics from TD-W8970 router. 
Home-page: https://github.com/morsisko/TD-W8970
Author: morsisko
License: MIT
Platform: UNKNOWN
Classifier: License :: OSI Approved :: MIT License
Classifier: Programming Language :: Python
Classifier: Programming Language :: Python :: 3
Classifier: Development Status :: 5 - Production/Stable
